pplint/__init__.py
pplint/cmd/__init__.py
pplint/cmd/analyze.py
pplint/cmd/init.py
pplint/manager/AnalyzeManager.py
pplint/manager/__init__.py
pplint/model/Location.py
pplint/model/Parameters.py
pplint/model/Problem.py
pplint/model/__init__.py
pplint/output/HtmlWriter.py
pplint/output/Result.py
pplint/output/XmlWriter.py
pplint/output/__init__.py
pplint/rules/ChineseRule.py
pplint/rules/RACRule.py
pplint/rules/__init__.py
pplint/util/__init__.py
pplint/util/fileUtil.py
pplint/util/gitUtil.py
pplint/util/sysUtil.py
pplint-1.0.dist-info/METADATA
pplint-1.0.dist-info/WHEEL
pplint-1.0.dist-info/top_level.txt
pplint-1.0.dist-info/RECORD
