Metadata-Version: 2.1
Name: pplint
Version: 1.0
Summary: Thie is localLint of the setup
Home-page: UNKNOWN
Author: liudeping
Author-email: liudeping@bytedance.com
License: UNKNOWN
Platform: UNKNOWN
Requires-Dist: GitPython (>=3.1.8)
Requires-Dist: unidiff (>=0.6.0)
